progaf/Application.py
progaf/BlobDetector.py
progaf/Camera.py
progaf/CentroidTracker.py
progaf/Detector.py
progaf/FaceDetector.py
progaf/FaceMeshDetector.py
progaf/HandDetector.py
progaf/LaserDetector.py
progaf/Panda3DApp.py
progaf/Profiler.py
progaf/Projector.py
progaf/PyGameApp.py
progaf/RectDetector.py
progaf/ShapeDetector.py
progaf/ShapeFactory.py
progaf/__init__.py
progaf-0.2.0rc3.dist-info/LICENSE
progaf-0.2.0rc3.dist-info/METADATA
progaf-0.2.0rc3.dist-info/WHEEL
progaf-0.2.0rc3.dist-info/top_level.txt
progaf-0.2.0rc3.dist-info/RECORD
