Metadata-Version: 2.1
Name: progaf
Version: 0.2.0rc3
Summary: Projection Games Framework
Home-page: https://github.com/jcfandinocal/progaf
Author: Keko
Author-email: jcfandinocal@gmail.com
License: UNKNOWN
Project-URL: Bug Tracker, https://github.com/jcfandinocal/progaf
Platform: UNKNOWN
Classifier: Programming Language :: Python :: 3
Classifier: License :: OSI Approved :: GNU General Public License v3 (GPLv3)
Classifier: Operating System :: OS Independent
Requires-Python: >=3.6
Requires-Dist: numpy
Requires-Dist: opencv-python
Requires-Dist: pygame
Requires-Dist: scipy
Requires-Dist: panda3d
Requires-Dist: mediapipe
